{
  "_format": "hh-sol-cache-2",
  "files": {
    "/home/baobg/week3/back/web3-blog/contracts/Blog.sol": {
      "lastModificationDate": 1679825781720,
      "contentHash": "612b0312db13484a21b4c8927385f257",
      "sourceName": "contracts/Blog.sol",
      "solcConfig": {
        "version": "0.8.4",
        "settings": {
          "optimizer": {
            "enabled": false,
            "runs": 200
          },
          "outputSelection": {
            "*": {
              "*": [
                "abi",
                "evm.bytecode",
                "evm.deployedBytecode",
                "evm.methodIdentifiers",
                "metadata"
              ],
              "": [
                "ast"
              ]
            }
          }
        }
      },
      "imports": [
        "hardhat/console.sol",
        "@openzeppelin/contracts/utils/Counters.sol"
      ],
      "versionPragmas": [
        "^0.8.0"
      ],
      "artifacts": [
        "Blog"
      ]
    },
    "/home/baobg/week3/back/web3-blog/node_modules/hardhat/console.sol": {
      "lastModificationDate": 1679275953106,
      "contentHash": "4ff3cd2f6272c9a6516e9ee4f2b967d3",
      "sourceName": "hardhat/console.sol",
      "solcConfig": {
        "version": "0.8.4",
        "settings": {
          "optimizer": {
            "enabled": false,
            "runs": 200
          },
          "outputSelection": {
            "*": {
              "*": [
                "abi",
                "evm.bytecode",
                "evm.deployedBytecode",
                "evm.methodIdentifiers",
                "metadata"
              ],
              "": [
                "ast"
              ]
            }
          }
        }
      },
      "imports": [],
      "versionPragmas": [
        ">= 0.4.22 <0.9.0"
      ],
      "artifacts": [
        "console"
      ]
    },
    "/home/baobg/week3/back/web3-blog/node_modules/@openzeppelin/contracts/utils/Counters.sol": {
      "lastModificationDate": 1679275952258,
      "contentHash": "74654e3ae5d7f39555055dfe244dab7a",
      "sourceName": "@openzeppelin/contracts/utils/Counters.sol",
      "solcConfig": {
        "version": "0.8.4",
        "settings": {
          "optimizer": {
            "enabled": false,
            "runs": 200
          },
          "outputSelection": {
            "*": {
              "*": [
                "abi",
                "evm.bytecode",
                "evm.deployedBytecode",
                "evm.methodIdentifiers",
                "metadata"
              ],
              "": [
                "ast"
              ]
            }
          }
        }
      },
      "imports": [],
      "versionPragmas": [
        "^0.8.0"
      ],
      "artifacts": [
        "Counters"
      ]
    }
  }
}
